{
    "configurations": [
        {
            "name": "Mac",
            "includePath": [
                "${workspaceFolder}/**",
                "/usr/local/Cellar/eosio.cdt/1.8.0/opt/eosio.cdt/include/eosiolib/core"
            ],
            "defines": [],
            "macFrameworkPath": [
                "/Library/Developer/CommandLineTools/SDKs/MacOSX10.15.sdk/System/Library/Frameworks"
            ],
            "compilerPath": "/usr/bin/clang",
            "cStandard": "c11",
            "cppStandard": "c++98",
            "intelliSenseMode": "macos-clang-x64"
        }
    ],
    "version": 4
}